streamer/__init__.py
streamer/cv_viewer/__init__.py
streamer/cv_viewer/cv_viewer.py
streamer/recorder/__init__.py
streamer/recorder/recorder.py
streamer/recorder/stream_writer.py
streamer/streamer/__init__.py
streamer/streamer/stream_iter.py
streamer/streamer/streamer.py
streamer/tools/__init__.py
streamer/tools/video_concat/__init__.py
streamer/tools/video_concat/video_concat.py
streamer/util/__init__.py
streamer/util/utils.py
pyclay_streamer-0.1.4.dist-info/LICENSE
pyclay_streamer-0.1.4.dist-info/METADATA
pyclay_streamer-0.1.4.dist-info/WHEEL
pyclay_streamer-0.1.4.dist-info/top_level.txt
pyclay_streamer-0.1.4.dist-info/RECORD
